this_platform/__init__.py
this_platform/__main__.py
this_platform-0.5.0.dist-info/METADATA
this_platform-0.5.0.dist-info/WHEEL
this_platform-0.5.0.dist-info/entry_points.txt
this_platform-0.5.0.dist-info/RECORD
